LINEBOOP/__init__.py
LINEBOOP/api.py
LINEBOOP/client.py
LINEBOOP/config.py
LINEBOOP/cube.py
LINEBOOP/e2ee.py
LINEBOOP/exceptions.py
LINEBOOP/helpers.py
LINEBOOP/hooks.py
LINEBOOP/models.py
LINEBOOP/object.py
LINEBOOP/poll.py
LINEBOOP/server.py
LINEBOOP/thrift.py
LINEBOOP/timeline.py
LINEBOOP/timelineBiz.py
LINEBOOP/BIZ/__init__.py
LINEBOOP/BIZ/TL/ST.py
LINEBOOP/BIZ/TL/__init__.py
LINEBOOP/dyher/__init__.py
LINEBOOP/dyher/conn.py
LINEBOOP/dyher/connManager.py
LINEBOOP/hksc/__init__.py
LINEBOOP/hksc/database.py
LINEBOOP/hksc/events.py
LINEBOOP/hksc/types.py
LINEBOOP/hksc/utility.py
LINEBOOP/serializers/DummyProtocol.py
LINEBOOP/serializers/__init__.py
LINEBOOP/services/AccessTokenRefreshService.py
LINEBOOP/services/AccountAuthFactorEapConnectService.py
LINEBOOP/services/AuthService.py
LINEBOOP/services/BaseService.py
LINEBOOP/services/BotExternalService.py
LINEBOOP/services/BuddyService.py
LINEBOOP/services/CallService.py
LINEBOOP/services/ChannelService.py
LINEBOOP/services/ChatAppService.py
LINEBOOP/services/E2EEKeyBackupService.py
LINEBOOP/services/HomeSafetyCheckService.py
LINEBOOP/services/InterlockService.py
LINEBOOP/services/LiffService.py
LINEBOOP/services/LoginService.py
LINEBOOP/services/OaMembershipService.py
LINEBOOP/services/PrimaryAccountInitService.py
LINEBOOP/services/PrimaryQrCodeMigrationLongPollingService.py
LINEBOOP/services/PrimaryQrCodeMigrationPreparationService.py
LINEBOOP/services/PwlessPrimaryRegistrationService.py
LINEBOOP/services/RelationService.py
LINEBOOP/services/SearchService.py
LINEBOOP/services/SecondaryPwlessLoginPermitNoticeService.py
LINEBOOP/services/SecondaryPwlessLoginService.py
LINEBOOP/services/SettingsService.py
LINEBOOP/services/ShopAuthService.py
LINEBOOP/services/ShopService.py
LINEBOOP/services/SquareBotService.py
LINEBOOP/services/SquareLiveTalkService.py
LINEBOOP/services/SquareService.py
LINEBOOP/services/TalkService.py
LINEBOOP/services/TestService.py
LINEBOOP/services/__init__.py
LINEBOOP-2.0.0.dist-info/LICENSE
LINEBOOP-2.0.0.dist-info/METADATA
LINEBOOP-2.0.0.dist-info/WHEEL
LINEBOOP-2.0.0.dist-info/top_level.txt
LINEBOOP-2.0.0.dist-info/RECORD
