Metadata-Version: 2.1
Name: LINEBOOP
Version: 2.0.0
Summary: LINE API! Upgrade Proxy
Home-page: https://github.com/DeachSword/CHRLINE
Author: DeachSword
Classifier: Programming Language :: Python :: 3.6
License-File: LICENSE
Requires-Dist: pycryptodome ==3.9.8
Requires-Dist: xxhash
Requires-Dist: rsa
Requires-Dist: requests
Requires-Dist: python-axolotl-curve25519
Requires-Dist: httpx[http2]
Requires-Dist: h2 >=3.2.0
Requires-Dist: gevent
Requires-Dist: cryptography
Requires-Dist: thrift
Requires-Dist: qrcode
Requires-Dist: Image
